Metadata-Version: 1.1
Name: blocktrail-sdk
Version: 1.0.5
Summary: BlockTrail's Developer Friendly API binding for Python
Home-page: https://www.blocktrail.com/api/docs/lang/python
Author: Ruben de Vries
Author-email: ruben@blocktrail.com
License: UNKNOWN
Platform: UNKNOWN
Classifier: Development Status :: 5 - Production/Stable
Classifier: Environment :: Console
Classifier: Environment :: Web Environment
Classifier: Intended Audience :: Developers
Classifier: Programming Language :: Python
Classifier: License :: OSI Approved :: MIT License
